{
  "db_name": "PostgreSQL",
  "query": "SELECT name, id FROM unifi_clients_mapping WHERE mac_address = $1",
  "describe": {
    "columns": [
      {
        "ordinal": 0,
        "name": "name",
        "type_info": "Text"
      },
      {
        "ordinal": 1,
        "name": "id",
        "type_info": "Uuid"
      }
    ],
    "parameters": {
      "Left": [
        "Text"
      ]
    },
    "nullable": [
      false,
      false
    ]
  },
  "hash": "f48cdf80041fe94971a869b8a36bac553ed444ddc0f19206f7ba3b2a2ded724c"
}
